crawto_doc/__init__.py
crawto_doc/__main__.py
crawto_doc/crawto_doc.py
tests/__init__.py
tests/test_blank_class/__init__.py
tests/test_blank_class/results_test_class.py
tests/test_blank_class/start_test_class.py
tests/test_blank_class/test_class.py
tests/test_blank_function/__init__.py
tests/test_blank_function/results_test_function.py
tests/test_blank_function/start_test_function.py
tests/test_blank_function/test_function.py
tests/test_crawto_doc/__init__.py
tests/test_crawto_doc/results_test_crawto_doc.py
tests/test_crawto_doc/start_test_crawto_doc.py
tests/test_crawto_doc/test_crawto_doc.py
crawto_quality-0.0.10.dist-info/License.txt
crawto_quality-0.0.10.dist-info/METADATA
crawto_quality-0.0.10.dist-info/WHEEL
crawto_quality-0.0.10.dist-info/entry_points.txt
crawto_quality-0.0.10.dist-info/top_level.txt
crawto_quality-0.0.10.dist-info/RECORD
