Metadata-Version: 2.1
Name: crawto-quality
Version: 0.0.10
Summary: UNKNOWN
Home-page: https://chiselapp.com/user/Crawftv/repository/crawto-quality/home
Author: Crawford Collins
License: UNKNOWN
Platform: UNKNOWN
Classifier: Programming Language :: Python :: 3
Classifier: Operating System :: OS Independent
Requires-Python: >=3.7
Requires-Dist: astor
